uipath_connectors/salesforce_sfdc/__init__.py
uipath_connectors/salesforce_sfdc/client.py
uipath_connectors/salesforce_sfdc/errors.py
uipath_connectors/salesforce_sfdc/py.typed
uipath_connectors/salesforce_sfdc/types.py
uipath_connectors/salesforce_sfdc/api/__init__.py
uipath_connectors/salesforce_sfdc/api/attachment_download/__init__.py
uipath_connectors/salesforce_sfdc/api/attachment_download/download_file.py
uipath_connectors/salesforce_sfdc/api/attachment_link/__init__.py
uipath_connectors/salesforce_sfdc/api/attachment_link/add_file_to_record.py
uipath_connectors/salesforce_sfdc/api/create_bulk_job/__init__.py
uipath_connectors/salesforce_sfdc/api/create_bulk_job/create_bulk_job.py
uipath_connectors/salesforce_sfdc/api/create_query_job/__init__.py
uipath_connectors/salesforce_sfdc/api/create_query_job/create_query_job.py
uipath_connectors/salesforce_sfdc/api/curated_account/__init__.py
uipath_connectors/salesforce_sfdc/api/curated_account/create_account.py
uipath_connectors/salesforce_sfdc/api/curated_account/get_account_by_id.py
uipath_connectors/salesforce_sfdc/api/curated_account/update_account.py
uipath_connectors/salesforce_sfdc/api/curated_contact/__init__.py
uipath_connectors/salesforce_sfdc/api/curated_contact/create_contact.py
uipath_connectors/salesforce_sfdc/api/curated_contact/get_contact_by_id.py
uipath_connectors/salesforce_sfdc/api/curated_contact/update_contact.py
uipath_connectors/salesforce_sfdc/api/curated_lead/__init__.py
uipath_connectors/salesforce_sfdc/api/curated_lead/create_lead.py
uipath_connectors/salesforce_sfdc/api/curated_lead/get_lead_by_id.py
uipath_connectors/salesforce_sfdc/api/curated_lead/update_lead.py
uipath_connectors/salesforce_sfdc/api/curated_opportunity/__init__.py
uipath_connectors/salesforce_sfdc/api/curated_opportunity/create_opportunity.py
uipath_connectors/salesforce_sfdc/api/curated_opportunity/get_opportunity_by_id.py
uipath_connectors/salesforce_sfdc/api/curated_soql_query/__init__.py
uipath_connectors_salesforce_sfdc-1.11.17.dev12.dist-info/METADATA
uipath_connectors_salesforce_sfdc-1.11.17.dev12.dist-info/WHEEL
uipath_connectors_salesforce_sfdc-1.11.17.dev12.dist-info/entry_points.txt
uipath_connectors_salesforce_sfdc-1.11.17.dev12.dist-info/top_level.txt
uipath_connectors_salesforce_sfdc-1.11.17.dev12.dist-info/RECORD
